LICENSE
MANIFEST.in
README.markdown
VERSION
setup.py
version.py
django_mga_schemata.egg-info/PKG-INFO
django_mga_schemata.egg-info/SOURCES.txt
django_mga_schemata.egg-info/dependency_links.txt
django_mga_schemata.egg-info/top_level.txt
django_schemata/__init__.py
django_schemata/middleware.py
django_schemata/models.py
django_schemata/tests.py
django_schemata/management/__init__.py
django_schemata/management/commands/__init__.py
django_schemata/management/commands/manage_schemata.py
django_schemata/management/commands/migrate_schemata.py
django_schemata/management/commands/sync_schemata.py
django_schemata/oracle_backend/__init__.py
django_schemata/oracle_backend/base.py
django_schemata/postgresql_backend/__init__.py
django_schemata/postgresql_backend/base.py